setup.py
tellme/__init__.py
tellme/compat.py
tellme/encoders.py
tellme/exceptions.py
tellme/formatters.py
tellme/reporters.py
tellme/utilities.py
tellme.egg-info/PKG-INFO
tellme.egg-info/SOURCES.txt
tellme.egg-info/dependency_links.txt
tellme.egg-info/not-zip-safe
tellme.egg-info/requires.txt
tellme.egg-info/top_level.txt