Metadata-Version: 1.1
Name: tellme
Version: 0.1.4
Summary: A toolkit for generating user-facing reports from things happening in code.
Home-page: http://okfn.org
Author: Open Knowledge Foundation
Author-email: info@okfn.org
License: MIT
Platform: UNKNOWN
Classifier: Development Status :: 4 - Beta
Classifier: Environment :: Web Environment
Classifier: Intended Audience :: Developers
Classifier: License :: OSI Approved :: MIT License
Classifier: Operating System :: OS Independent
Classifier: Programming Language :: Python :: 2
Classifier: Programming Language :: Python :: 3
Classifier: Topic :: Internet :: WWW/HTTP :: Dynamic Content
Classifier: Topic :: Software Development :: Libraries :: Python Modules
